jupyter_fsspec/__init__.py
jupyter_fsspec/_version.py
jupyter_fsspec/api-static.html
jupyter_fsspec/api_schema.yml
jupyter_fsspec/client.py
jupyter_fsspec/exceptions.py
jupyter_fsspec/file_manager.py
jupyter_fsspec/handlers.py
jupyter_fsspec/helper.py
jupyter_fsspec/models.py
jupyter_fsspec/utils.py
jupyter_fsspec/scripts/update_api_schema.py
jupyter_fsspec/tests/__init__.py
jupyter_fsspec/tests/test_api.py
jupyter_fsspec/tests/test_client.py
jupyter_fsspec/tests/test_end.png
jupyter_fsspec/tests/unit/test_filesystem_manager.py
jupyter_fsspec-0.4.1.data/data/etc/jupyter/jupyter_server_config.d/jupyter_fsspec.json
jupyter_fsspec-0.4.1.data/data/share/jupyter/labextensions/jupyterFsspec/package.json
jupyter_fsspec-0.4.1.data/data/share/jupyter/labextensions/jupyterFsspec/schemas/jupyterFsspec/package.json.orig
jupyter_fsspec-0.4.1.data/data/share/jupyter/labextensions/jupyterFsspec/schemas/jupyterFsspec/plugin.json
jupyter_fsspec-0.4.1.data/data/share/jupyter/labextensions/jupyterFsspec/static/287.50f0de0337a537f479be.js
jupyter_fsspec-0.4.1.data/data/share/jupyter/labextensions/jupyterFsspec/static/287.50f0de0337a537f479be.js.LICENSE.txt
jupyter_fsspec-0.4.1.data/data/share/jupyter/labextensions/jupyterFsspec/static/384.8df34303dc6a6d2da259.js
jupyter_fsspec-0.4.1.data/data/share/jupyter/labextensions/jupyterFsspec/static/403.8b468423eb59b8071fb8.js
jupyter_fsspec-0.4.1.data/data/share/jupyter/labextensions/jupyterFsspec/static/590.eb30de61b7dba6782fdb.js
jupyter_fsspec-0.4.1.data/data/share/jupyter/labextensions/jupyterFsspec/static/627.9a32a50e5b86a7b1f3f6.js
jupyter_fsspec-0.4.1.data/data/share/jupyter/labextensions/jupyterFsspec/static/728.eaed3f2e0b36ee217a85.js
jupyter_fsspec-0.4.1.data/data/share/jupyter/labextensions/jupyterFsspec/static/742.e0a83c8bcc05b569327d.js
jupyter_fsspec-0.4.1.data/data/share/jupyter/labextensions/jupyterFsspec/static/960.f3fa70e26c674fce49ea.js
jupyter_fsspec-0.4.1.dist-info/METADATA
jupyter_fsspec-0.4.1.dist-info/WHEEL
jupyter_fsspec-0.4.1.dist-info/licenses/LICENSE
jupyter_fsspec-0.4.1.dist-info/RECORD
