Metadata-Version: 2.4
Name: jupyter_fsspec
Version: 0.4.1
Summary: A Jupyter interface for fsspec.
Project-URL: Homepage, https://github.com/fsspec/jupyter-fsspec
Project-URL: Bug Tracker, https://github.com/fsspec/jupyter-fsspec/issues
Project-URL: Repository, https://github.com/fsspec/jupyter-fsspec.git
Author: Jupyter Fsspec contributors
License: BSD 3-Clause License
License-File: LICENSE
Keywords: jupyter,jupyterlab,jupyterlab-extension
Classifier: Framework :: Jupyter
Classifier: Framework :: Jupyter :: JupyterLab
Classifier: Framework :: Jupyter :: JupyterLab :: 4
Classifier: Framework :: Jupyter :: JupyterLab :: Extensions
Classifier: Framework :: Jupyter :: JupyterLab :: Extensions :: Prebuilt
Classifier: License :: OSI Approved :: BSD License
Classifier: Programming Language :: Python
Classifier: Programming Language :: Python :: 3
Classifier: Programming Language :: Python :: 3.8
Classifier: Programming Language :: Python :: 3.9
Classifier: Programming Language :: Python :: 3.10
Classifier: Programming Language :: Python :: 3.11
Classifier: Programming Language :: Python :: 3.12
Requires-Python: >=3.8
Requires-Dist: fsspec
Requires-Dist: jupyter-server<3,>=2.4.0
Requires-Dist: pydantic>=2
Provides-Extra: dev
Requires-Dist: hatch; extra == 'dev'
Requires-Dist: pre-commit; extra == 'dev'
Requires-Dist: ruff==0.7.2; extra == 'dev'
Provides-Extra: docs
Requires-Dist: myst-parser; extra == 'docs'
Requires-Dist: sphinx; extra == 'docs'
Requires-Dist: sphinx-rtd-theme; extra == 'docs'
Provides-Extra: test
Requires-Dist: aiobotocore<3.0.0,>=2.5.4; extra == 'test'
Requires-Dist: boto3; extra == 'test'
Requires-Dist: coverage; extra == 'test'
Requires-Dist: fsspec; extra == 'test'
Requires-Dist: moto[server]>=5; extra == 'test'
Requires-Dist: pytest; extra == 'test'
Requires-Dist: pytest-asyncio; extra == 'test'
Requires-Dist: pytest-cov; extra == 'test'
Requires-Dist: pytest-jupyter; extra == 'test'
Requires-Dist: s3fs; extra == 'test'
